convomeld-0.1.8.dist-info/METADATA
convomeld-0.1.8.dist-info/WHEEL
convomeld-0.1.8.dist-info/entry_points.txt
convomeld-0.1.8.dist-info/licenses/LICENSE.md
convomeld/__init__.py
convomeld/__main__.py
convomeld/api.py
convomeld/cli.py
convomeld/constants.py
convomeld/converters.py
convomeld/convocat.py
convomeld/convoparse.py
convomeld/data/DemoRoriV3Quiz.joblib
convomeld/data/DemoRoriV3Quiz.xlsx
convomeld/data/DemoRoriV3Quiz_load_dataframes.py
convomeld/data/csv_converter_data/microlesson_examples.xlsx
convomeld/data/csv_converter_data/single_worksheet.csv
convomeld/data/csv_converter_data/single_worksheet.xlsx
convomeld/data/csv_converter_data/two_worksheets.xlsx
convomeld/data/data.yml
convomeld/data/rori_example_conversation.csv
convomeld/data/rori_example_conversation.xlsx
convomeld/data/rori_refactoring_test.rori.txt
convomeld/data/test/graphs/v2/merged/count_by_one_1_1+1_2+1_3.yml
convomeld/data/test/graphs/v2/merged/count_by_one_1_1+1_2.yml
convomeld/data/test/graphs/v2/merged/count_by_one_2_1+2_2+2_3.yml
convomeld/data/test/graphs/v2/merged/count_by_one_2_1+2_2.yml
convomeld/data/test/graphs/v2/merged/count_by_one_2_1+2_3.yml
convomeld/data/test/graphs/v2/merged/count_by_one_2_2+2_3.yml
convomeld/data/test/graphs/v2/parsed/count_by_one_1_1.yml
convomeld/data/test/graphs/v2/parsed/count_by_one_1_1_student_stop_early.yml
convomeld/data/test/graphs/v2/parsed/count_by_one_1_1_teacher_stop_early.yml
convomeld/data/test/graphs/v2/parsed/count_by_one_1_2.yml
convomeld/data/test/graphs/v2/parsed/count_by_one_1_3.yml
convomeld/data/test/graphs/v2/parsed/count_by_one_2_1.yml
convomeld/data/test/graphs/v2/parsed/count_by_one_2_2.yml
convomeld/data/test/graphs/v2/parsed/count_by_one_2_3.yml
convomeld/data/test/graphs/v2/parsed/count_by_one_2_student_stop_early_1.yml
convomeld/data/test/graphs/v2/parsed/count_by_one_2_student_stop_early_2.yml
convomeld/data/test/graphs/v2/parsed/count_by_one_2_student_stop_early_3.yml
convomeld/data/test/graphs/v3/merged/count_by_one_1_1+1_2+1_3.yml
convomeld/data/test/graphs/v3/merged/count_by_one_1_1+1_2.yml
convomeld/data/test/graphs/v3/merged/count_by_one_2_1+2_2+2_3.yml
convomeld-0.1.8.dist-info/RECORD
